SeleniumScreenshots/__init__.py
SeleniumScreenshots/resources/add_dot.js
SeleniumScreenshots/resources/add_note.js
SeleniumScreenshots/resources/add_pointer.js
SeleniumScreenshots/resources/align_elements_horizontally.js
SeleniumScreenshots/resources/bootstrap_jquery.js
SeleniumScreenshots/resources/get_bounding_box.js
SeleniumScreenshots/resources/get_viewport_box.js
SeleniumScreenshots/resources/remove_element.js
SeleniumScreenshots/resources/update_element_style.js
robotframework_seleniumscreenshots-0.9.5.dist-info/METADATA
robotframework_seleniumscreenshots-0.9.5.dist-info/RECORD
robotframework_seleniumscreenshots-0.9.5.dist-info/WHEEL
robotframework_seleniumscreenshots-0.9.5.dist-info/top_level.txt
