Metadata-Version: 2.1
Name: robotframework-seleniumscreenshots
Version: 0.9.5
Summary: Robot Framework keyword library for capturing annotated screenshots with SeleniumLibrary
Home-page: https://github.com/datakurre/robotframework-seleniumscreenshots
Author: Asko Soukka
Author-email: asko.soukka@iki.fi
License: BSD-3-Clause
Keywords: robotframework selenium
Platform: UNKNOWN
Classifier: Intended Audience :: Developers
Classifier: Intended Audience :: Information Technology
Classifier: Framework :: Robot Framework
Classifier: Framework :: Robot Framework :: Library
Classifier: License :: OSI Approved :: BSD License
Classifier: Programming Language :: Python :: 2.7
Classifier: Programming Language :: Python :: 3.6
Classifier: Programming Language :: Python :: 3.7
Classifier: Topic :: Software Development :: Quality Assurance
Classifier: Topic :: Software Development :: Testing
Provides-Extra: docs
Provides-Extra: pillow
Provides-Extra: pil
